{
  "bm25_done": true,
  "bm25_implementation": "custom from-scratch Okapi BM25 (rank_bm25 package not installed)",
  "dense_possible": true,
  "dense_library_available": false,
  "dense_model_cached": false,
  "dense_model_paths": [],
  "hybrid_possible": true,
  "reranker_possible": true,
  "reranker_library_available": true,
  "reranker_model_cached": false,
  "reranker_model_paths": [],
  "nli_model_cached": true,
  "nli_model_path": "C:\\Users\\Administrator\\.cache\\huggingface\\hub\\models--cross-encoder--nli-deberta-base",
  "gpu_available": false,
  "sklearn_available": true,
  "scipy_available": true,
  "numpy_available": true,
  "pandas_available": true,
  "torch_available": true,
  "transformers_available": true,
  "n_chunks": 4747,
  "n_chunks_suitable_for_dense": true,
  "recommended_upgrade_order": [
    "1. Install sentence-transformers (pip install sentence-transformers) for dense retrieval",
    "2. Download a small dense model (e.g., all-MiniLM-L6-v2) for zero-shot dense retrieval",
    "3. Run dense retrieval on 4747 chunks (CPU-feasible, ~5-10 min)",
    "4. Combine BM25 + dense scores for hybrid retrieval (weighted sum or RRF)",
    "5. Use cached cross-encoder/nli-deberta-base as cross-encoder reranker (top-50 → top-10)",
    "6. Re-evaluate retrieval metrics (Recall@k, MRR) on hybrid + reranker"
  ],
  "expected_benefit": "Hybrid (BM25+dense) typically improves Recall@10 by 2-5%; cross-encoder reranker typically improves Recall@1 by 10-20%. Main benefit: better chunk-level precision (currently 25.45% oracle_chunk_not_retrieved failures).",
  "risk": "Dense retrieval on CPU is slow but feasible for 4747 chunks. No GPU available. Cross-encoder reranker on CPU is slower but still feasible for top-50 reranking."
}